litewave_logger/__init__.py
litewave_logger/celery.py
litewave_logger/middleware.py
litewave_logger/requests.py
litewave_logger-0.5.0.dist-info/METADATA
litewave_logger-0.5.0.dist-info/WHEEL
litewave_logger-0.5.0.dist-info/top_level.txt
litewave_logger-0.5.0.dist-info/RECORD
