Metadata-Version: 2.4
Name: litewave_logger
Version: 0.5.0
Summary: A lightweight logging library with context carry forward
Author: Litewave
Author-email: Sonu Sudhakaran <sonu@litewave.ai>
Requires-Python: >=3.6
Requires-Dist: requests
Requires-Dist: fastapi
Dynamic: author
Dynamic: requires-python
